{"trial_id": "0", "hyperparameters": {"space": [{"class_name": "Int", "config": {"name": "num_units", "default": null, "conditions": [], "min_value": 32, "max_value": 564, "step": 32, "sampling": null}}, {"class_name": "Choice", "config": {"name": "activation", "default": "relu", "conditions": [], "values": ["relu", "tanh"], "ordered": false}}, {"class_name": "Int", "config": {"name": "num_layers", "default": null, "conditions": [], "min_value": 1, "max_value": 5, "step": 1, "sampling": null}}, {"class_name": "Int", "config": {"name": "units_0", "default": null, "conditions": [], "min_value": 32, "max_value": 564, "step": 32, "sampling": null}}, {"class_name": "Boolean", "config": {"name": "dropout", "default": false, "conditions": []}}, {"class_name": "Float", "config": {"name": "lr", "default": 0.0001, "conditions": [], "min_value": 0.0001, "max_value": 0.01, "step": null, "sampling": "log"}}, {"class_name": "Int", "config": {"name": "units_1", "default": null, "conditions": [], "min_value": 32, "max_value": 564, "step": 32, "sampling": null}}, {"class_name": "Int", "config": {"name": "units_2", "default": null, "conditions": [], "min_value": 32, "max_value": 564, "step": 32, "sampling": null}}, {"class_name": "Int", "config": {"name": "units_3", "default": null, "conditions": [], "min_value": 32, "max_value": 564, "step": 32, "sampling": null}}], "values": {"num_units": 96, "activation": "relu", "num_layers": 4, "units_0": 128, "dropout": false, "lr": 0.0019324178253685884, "units_1": 32, "units_2": 32, "units_3": 32}}, "metrics": {"metrics": {"loss": {"direction": "min", "observations": [{"value": [0.0039971801452338696], "step": 1}]}, "mean_squared_error": {"direction": "min", "observations": [{"value": [0.0039971801452338696], "step": 1}]}, "val_loss": {"direction": "min", "observations": [{"value": [0.002320746658369899], "step": 1}]}, "val_mean_squared_error": {"direction": "min", "observations": [{"value": [0.002320746658369899], "step": 1}]}}}, "score": 0.002320746658369899, "best_step": 1, "status": "COMPLETED"}